{
  "elec_adult_suffrage": ["voting rights", "franchise", "adult citizens", "legal right to vote"],
  "elec_election_integrity": ["fair elections", "campaign conditions", "vote counting", "electoral misconduct"],
  "elec_elected_office_control": ["elected government", "unelected power", "public office", "civilian control"],
  "elec_opposition_association": ["opposition parties", "party organisation", "political association", "campaign freely"],
  "elec_alternative_information": ["independent media", "critical reporting", "news pluralism", "alternative sources"],
  "lib_law_predictability": ["predictable rules", "consistent enforcement", "legal certainty", "arbitrary law"],
  "lib_access_to_justice": ["legal remedy", "courts access", "fair hearing", "justice system"],
  "lib_civil_liberties": ["basic freedoms", "personal rights", "state interference", "civil rights"],
  "lib_judicial_independence": ["independent courts", "judge appointments", "political pressure on judges", "court autonomy"],
  "lib_executive_court_compliance": ["implement judgments", "obey court decisions", "adverse rulings", "court orders"],
  "lib_executive_constitutional_compliance": ["constitutional limits", "executive restraint", "constitutional rules", "abuse of power"],
  "lib_legislative_oversight": ["parliamentary scrutiny", "legislative committees", "question government", "assembly oversight"],
  "lib_oversight_body_independence": ["public watchdogs", "audit office", "ombudsman", "independent regulator"],
  "delib_reasoned_justification": ["policy explanation", "reasoned decisions", "public justification", "government reasoning"],
  "delib_counterargument_respect": ["respond to objections", "opposing arguments", "policy criticism", "alternative views"],
  "delib_consultation_breadth": ["public consultation", "stakeholder input", "hear affected groups", "consultation period"],
  "delib_common_good_justification": ["public interest", "common good", "sectional interests", "collective benefit"],
  "delib_public_deliberation": ["public debate", "reasoned discussion", "policy dialogue", "open debate"],
  "part_cso_autonomy": ["independent civic groups", "civil society freedom", "non-governmental organisations", "civic autonomy"],
  "part_cso_policy_consultation": ["civic organisations consulted", "policy influence", "government consultation", "organised interests"],
  "part_citizen_initiative_access": ["citizen proposal", "popular initiative", "petition mechanism", "agenda initiative"],
  "part_referendum_access": ["referendum", "popular vote", "direct vote", "ballot question"],
  "part_local_elected_power": ["municipal authority", "local government", "opposition mayors", "regional power"],
  "egal_equal_protection": ["group protection", "equal treatment", "discrimination", "minority protection"],
  "egal_civil_liberty_equality": ["unequal freedoms", "group liberties", "equal civil rights", "discriminatory restrictions"],
  "egal_justice_access_equality": ["equal court access", "justice inequality", "legal access by group", "fair remedy"],
  "egal_gender_power_equality": ["gender political power", "women influence", "gender equality", "political leadership"],
  "egal_socioeconomic_power_equality": ["wealth and political influence", "class power", "income groups", "economic privilege"],
  "egal_social_group_power_equality": ["minority political power", "social groups", "group influence", "political exclusion"],
  "egal_resource_access_equality": ["public resources", "education access", "health access", "unequal opportunities"],
  "cond_voter_turnout": ["election participation", "votes cast", "voting participation", "electoral turnout"],
  "cond_political_association_activity": ["association membership", "political groups", "independent organisations", "civic activity"],
  "cond_clean_government": ["public corruption", "misuse of office", "government integrity", "bribery"],
  "cond_women_parliament_share": ["female legislators", "women representatives", "gender representation", "parliament seats"],
  "cond_income_inequality": ["income distribution", "gini", "economic inequality", "income gap"],
  "ctx_gdp_per_capita_index": ["average income", "economic prosperity", "income per person", "living standards"],
  "ctx_gdp_growth": ["economic growth", "recession", "output change", "economy expansion"],
  "ctx_inflation": ["price increases", "cost of living", "consumer prices", "price growth"],
  "ctx_unemployment": ["joblessness", "employment conditions", "labour market", "without work"],
  "ctx_population_millions": ["inhabitants", "population size", "demographic size", "residents"],
  "ctx_urbanisation": ["urban population", "cities", "urbanisation", "city residents"],
  "ctx_life_expectancy": ["longevity", "health outcomes", "expected lifespan", "mortality"],
  "ctx_internet_use": ["online access", "digital connectivity", "internet users", "online communication"],
  "ctx_co2_per_capita": ["carbon emissions", "climate", "emissions per person", "CO2"],
  "ctx_net_migration_rate": ["immigration", "emigration", "population movement", "migration balance"]
}
